{
    "local_variable": {
        "1790517250": {
            "variable_dict": {
                "NEW_TIMER": {}, 
                "UNIT_ENTITY": {}
            }, 
            "variable_length_dict": {}
        }, 
        "2132258821": {
            "variable_dict": {
                "SFX_ENTITY": {
                    "effect": 0
                }, 
                "UNIT_ENTITY": {
                    "unit": 0
                }
            }, 
            "variable_length_dict": {
                "effect": 0, 
                "unit": 0
            }
        }
    }, 
    "trigger_dict": {
        "1790517250": {
            "action": [
                {
                    "action_type": "UNREG_TRIGGER", 
                    "args_list": [
                        {
                            "arg_type": 100178, 
                            "args_list": [], 
                            "sub_type": "CURRENT_DYNAMIC_TRIGGER_INSTANCE"
                        }
                    ], 
                    "bp": false, 
                    "element_id": 1790517250000006, 
                    "enable": true
                }, 
                {
                    "action_type": "APPLY_DAMAGE", 
                    "args_list": [
                        {
                            "arg_type": 100006, 
                            "args_list": [
                                [
                                    "UNIT_ENTITY", 
                                    "unit", 
                                    "local"
                                ]
                            ], 
                            "sub_type": 11
                        }, 
                        {
                            "arg_type": 100014, 
                            "args_list": [], 
                            "sub_type": "CUR_ABILITY"
                        }, 
                        {
                            "arg_type": 100006, 
                            "args_list": [], 
                            "sub_type": "DAMAGE_TARGET_UNIT"
                        }, 
                        {
                            "arg_type": 100064, 
                            "args_list": [
                                0
                            ], 
                            "sub_type": 1
                        }, 
                        {
                            "arg_type": 100000, 
                            "args_list": [
                                {
                                    "arg_type": 100000, 
                                    "args_list": [
                                        2.0
                                    ], 
                                    "sub_type": 1
                                }, 
                                {
                                    "arg_type": 100017, 
                                    "args_list": [
                                        "*"
                                    ], 
                                    "sub_type": 1
                                }, 
                                {
                                    "arg_type": 100000, 
                                    "args_list": [
                                        {
                                            "arg_type": 100006, 
                                            "args_list": [
                                                [
                                                    "UNIT_ENTITY", 
                                                    "unit", 
                                                    "local"
                                                ]
                                            ], 
                                            "sub_type": 11
                                        }, 
                                        {
                                            "arg_type": 100301, 
                                            "args_list": [
                                                "ATTR_RESULT"
                                            ], 
                                            "sub_type": 1
                                        }, 
                                        {
                                            "arg_type": 100042, 
                                            "args_list": [
                                                "attack_phy"
                                            ], 
                                            "sub_type": 1
                                        }
                                    ], 
                                    "sub_type": "GET_UNIT_ATTR"
                                }
                            ], 
                            "sub_type": "ARITHMETIC_OPERATION"
                        }, 
                        {
                            "arg_type": 100001, 
                            "args_list": [
                                true
                            ], 
                            "sub_type": 1
                        }
                    ], 
                    "bp": false, 
                    "element_id": 1790517250000013, 
                    "enable": true, 
                    "op_arg": [
                        {
                            "arg_type": 100001, 
                            "args_list": [
                                true
                            ], 
                            "sub_type": 1
                        }, 
                        {
                            "arg_type": 100001, 
                            "args_list": [
                                true
                            ], 
                            "sub_type": 1
                        }, 
                        {
                            "arg_type": 100001, 
                            "args_list": [
                                true
                            ], 
                            "sub_type": 1
                        }, 
                        null, 
                        null, 
                        null, 
                        null, 
                        null, 
                        null
                    ], 
                    "op_arg_enable": [
                        false, 
                        false, 
                        false, 
                        false, 
                        false, 
                        false, 
                        false, 
                        false, 
                        false
                    ]
                }, 
                {
                    "action_type": "SET_VARIABLE", 
                    "args_list": [
                        {
                            "arg_type": 100148, 
                            "args_list": [
                                [
                                    "SFX_ENTITY", 
                                    "effect", 
                                    "local"
                                ]
                            ], 
                            "sub_type": 4
                        }, 
                        {
                            "arg_type": 100148, 
                            "args_list": [
                                {
                                    "arg_type": 100066, 
                                    "args_list": [
                                        103211
                                    ], 
                                    "sub_type": 1
                                }, 
                                {
                                    "arg_type": 100006, 
                                    "args_list": [
                                        [
                                            "UNIT_ENTITY", 
                                            "unit", 
                                            "local"
                                        ]
                                    ], 
                                    "sub_type": 11
                                }, 
                                {
                                    "arg_type": 100003, 
                                    "args_list": [
                                        "origin"
                                    ], 
                                    "sub_type": 1
                                }, 
                                {
                                    "arg_type": 100001, 
                                    "args_list": [
                                        true
                                    ], 
                                    "sub_type": 1
                                }, 
                                {
                                    "arg_type": 100001, 
                                    "args_list": [
                                        true
                                    ], 
                                    "sub_type": 1
                                }
                            ], 
                            "op_arg": [
                                null, 
                                null, 
                                null, 
                                null
                            ], 
                            "op_arg_enable": [
                                false, 
                                false, 
                                false, 
                                false
                            ], 
                            "sub_type": "CREATE_SFX_ON_UNIT"
                        }
                    ], 
                    "bp": false, 
                    "element_id": 1790517250000025, 
                    "enable": true
                }, 
                {
                    "action_type": "ADD_STATE", 
                    "args_list": [
                        {
                            "arg_type": 100006, 
                            "args_list": [
                                [
                                    "UNIT_ENTITY", 
                                    "unit", 
                                    "local"
                                ]
                            ], 
                            "sub_type": 11
                        }, 
                        {
                            "arg_type": 100075, 
                            "args_list": [
                                2
                            ], 
                            "sub_type": 1
                        }
                    ], 
                    "bp": false, 
                    "element_id": 1790517250000055, 
                    "enable": true
                }, 
                {
                    "action_type": "ADD_STATE", 
                    "args_list": [
                        {
                            "arg_type": 100006, 
                            "args_list": [
                                [
                                    "UNIT_ENTITY", 
                                    "unit", 
                                    "local"
                                ]
                            ], 
                            "sub_type": 11
                        }, 
                        {
                            "arg_type": 100075, 
                            "args_list": [
                                8192
                            ], 
                            "sub_type": 1
                        }
                    ], 
                    "bp": false, 
                    "element_id": 1790517250000059, 
                    "enable": true
                }, 
                {
                    "action_type": "CREATE_STRAIGHT_MOVER", 
                    "args_list": [
                        {
                            "arg_type": 100006, 
                            "args_list": [
                                [
                                    "UNIT_ENTITY", 
                                    "unit", 
                                    "local"
                                ]
                            ], 
                            "sub_type": 11
                        }, 
                        {
                            "arg_type": 100225, 
                            "args_list": [
                                {
                                    "arg_type": 100004, 
                                    "args_list": [
                                        {
                                            "arg_type": 100006, 
                                            "args_list": [
                                                [
                                                    "UNIT_ENTITY", 
                                                    "unit", 
                                                    "local"
                                                ]
                                            ], 
                                            "sub_type": 11
                                        }
                                    ], 
                                    "sub_type": "UNIT_ENTITY_POINT"
                                }, 
                                {
                                    "arg_type": 100004, 
                                    "args_list": [
                                        {
                                            "arg_type": 100006, 
                                            "args_list": [], 
                                            "sub_type": "DAMAGE_TARGET_UNIT"
                                        }
                                    ], 
                                    "sub_type": "UNIT_ENTITY_POINT"
                                }
                            ], 
                            "sub_type": "GET_POINTS_ANGLE"
                        }, 
                        {
                            "arg_type": 100000, 
                            "args_list": [
                                1000.0
                            ], 
                            "sub_type": 1
                        }, 
                        {
                            "arg_type": 100000, 
                            "args_list": [
                                1000.0
                            ], 
                            "sub_type": 1
                        }, 
                        {
                            "arg_type": 100000, 
                            "args_list": [
                                0.0
                            ], 
                            "sub_type": 1
                        }, 
                        {
                            "arg_type": 100022, 
                            "args_list": [], 
                            "sub_type": 1
                        }, 
                        {
                            "arg_type": 100022, 
                            "args_list": [], 
                            "sub_type": 1
                        }, 
                        {
                            "arg_type": 100022, 
                            "args_list": [], 
                            "sub_type": 1
                        }, 
                        {
                            "arg_type": 100022, 
                            "args_list": [], 
                            "sub_type": 1
                        }, 
                        {
                            "arg_type": 100022, 
                            "args_list": [], 
                            "sub_type": 1
                        }
                    ], 
                    "bp": false, 
                    "element_id": 1790517250000003, 
                    "enable": true, 
                    "fake_op": [], 
                    "local_var": {
                        "__tuple__": true, 
                        "items": [
                            {}, 
                            {}
                        ]
                    }, 
                    "op_arg": [
                        null, 
                        null, 
                        null, 
                        null, 
                        null, 
                        null, 
                        null, 
                        {
                            "arg_type": 100001, 
                            "args_list": [
                                true
                            ], 
                            "sub_type": 1
                        }, 
                        {
                            "arg_type": 100001, 
                            "args_list": [
                                true
                            ], 
                            "sub_type": 1
                        }, 
                        {
                            "arg_type": 100001, 
                            "args_list": [
                                true
                            ], 
                            "sub_type": 1
                        }, 
                        null, 
                        {
                            "arg_type": 100001, 
                            "args_list": [
                                true
                            ], 
                            "sub_type": 1
                        }, 
                        null, 
                        null, 
                        null, 
                        null, 
                        null
                    ], 
                    "op_arg_enable": [
                        false, 
                        false, 
                        false, 
                        false, 
                        false, 
                        false, 
                        false, 
                        false, 
                        false, 
                        true, 
                        false, 
                        false, 
                        false, 
                        false, 
                        false, 
                        false, 
                        false
                    ]
                }, 
                {
                    "action_type": "PLAY_ANIMATION", 
                    "args_list": [
                        {
                            "arg_type": 100006, 
                            "args_list": [
                                [
                                    "UNIT_ENTITY", 
                                    "unit", 
                                    "local"
                                ]
                            ], 
                            "sub_type": 11
                        }, 
                        {
                            "arg_type": 100003, 
                            "args_list": [
                                "walk"
                            ], 
                            "sub_type": 1
                        }, 
                        {
                            "arg_type": 100000, 
                            "args_list": [
                                1.0
                            ], 
                            "sub_type": 1
                        }, 
                        {
                            "arg_type": 100000, 
                            "args_list": [
                                0.0
                            ], 
                            "sub_type": 1
                        }, 
                        {
                            "arg_type": 100000, 
                            "args_list": [
                                -1.0
                            ], 
                            "sub_type": 1
                        }, 
                        {
                            "arg_type": 100001, 
                            "args_list": [
                                true
                            ], 
                            "sub_type": 1
                        }, 
                        {
                            "arg_type": 100001, 
                            "args_list": [
                                false
                            ], 
                            "sub_type": 1
                        }
                    ], 
                    "bp": false, 
                    "element_id": 1790517250000037, 
                    "enable": true, 
                    "op_arg": [
                        {
                            "arg_type": 100000, 
                            "args_list": [
                                -1.0
                            ], 
                            "sub_type": 1
                        }, 
                        {
                            "arg_type": 100001, 
                            "args_list": [
                                false
                            ], 
                            "sub_type": 1
                        }
                    ], 
                    "op_arg_enable": [
                        false, 
                        false
                    ]
                }, 
                {
                    "action_type": "FOLLOW_OBJECT_PLAY_3D_SOUND_FOR_PLAYER", 
                    "args_list": [
                        null, 
                        {
                            "arg_type": 100084, 
                            "args_list": [
                                134267919
                            ], 
                            "sub_type": 1
                        }, 
                        {
                            "arg_type": 100006, 
                            "args_list": [
                                [
                                    "UNIT_ENTITY", 
                                    "unit", 
                                    "local"
                                ]
                            ], 
                            "sub_type": 11
                        }, 
                        {
                            "arg_type": 100001, 
                            "args_list": [
                                false
                            ], 
                            "sub_type": 1
                        }
                    ], 
                    "bp": false, 
                    "element_id": 1790517250000072, 
                    "enable": true, 
                    "op_arg": [
                        null, 
                        null, 
                        {
                            "arg_type": 100001, 
                            "args_list": [
                                true
                            ], 
                            "sub_type": 1
                        }, 
                        null, 
                        null, 
                        null, 
                        null
                    ], 
                    "op_arg_enable": [
                        false, 
                        false, 
                        false, 
                        false, 
                        false, 
                        false, 
                        false
                    ]
                }, 
                {
                    "action_type": "RUN_ONCE_TIMER_NO_SAVE", 
                    "args_list": [
                        {
                            "arg_type": 100000, 
                            "args_list": [
                                1.0
                            ], 
                            "sub_type": 1
                        }, 
                        {
                            "arg_type": 100022, 
                            "args_list": [
                                {
                                    "action_type": "DELETE_SFX_ENTITY", 
                                    "args_list": [
                                        {
                                            "arg_type": 100148, 
                                            "args_list": [
                                                [
                                                    "SFX_ENTITY", 
                                                    "effect", 
                                                    "local"
                                                ]
                                            ], 
                                            "sub_type": 4
                                        }
                                    ], 
                                    "bp": false, 
                                    "element_id": 1790517250000032, 
                                    "enable": true, 
                                    "op_arg": [
                                        {
                                            "arg_type": 100001, 
                                            "args_list": [
                                                true
                                            ], 
                                            "sub_type": 1
                                        }
                                    ], 
                                    "op_arg_enable": [
                                        false
                                    ]
                                }, 
                                {
                                    "action_type": "REMOVE_STATE", 
                                    "args_list": [
                                        {
                                            "arg_type": 100006, 
                                            "args_list": [
                                                [
                                                    "UNIT_ENTITY", 
                                                    "unit", 
                                                    "local"
                                                ]
                                            ], 
                                            "sub_type": 11
                                        }, 
                                        {
                                            "arg_type": 100075, 
                                            "args_list": [
                                                2
                                            ], 
                                            "sub_type": 1
                                        }
                                    ], 
                                    "bp": false, 
                                    "element_id": 1790517250000057, 
                                    "enable": true
                                }, 
                                {
                                    "action_type": "REMOVE_STATE", 
                                    "args_list": [
                                        {
                                            "arg_type": 100006, 
                                            "args_list": [
                                                [
                                                    "UNIT_ENTITY", 
                                                    "unit", 
                                                    "local"
                                                ]
                                            ], 
                                            "sub_type": 11
                                        }, 
                                        {
                                            "arg_type": 100075, 
                                            "args_list": [
                                                8192
                                            ], 
                                            "sub_type": 1
                                        }
                                    ], 
                                    "bp": false, 
                                    "element_id": 1790517250000063, 
                                    "enable": true
                                }, 
                                {
                                    "action_type": "STOP_ANIMATION", 
                                    "args_list": [
                                        {
                                            "arg_type": 100006, 
                                            "args_list": [
                                                [
                                                    "UNIT_ENTITY", 
                                                    "unit", 
                                                    "local"
                                                ]
                                            ], 
                                            "sub_type": 11
                                        }, 
                                        {
                                            "arg_type": 100003, 
                                            "args_list": [
                                                "walk"
                                            ], 
                                            "sub_type": 1
                                        }
                                    ], 
                                    "bp": false, 
                                    "element_id": 1790517250000045, 
                                    "enable": true
                                }, 
                                {
                                    "action_type": "TRANS_UNIT", 
                                    "args_list": [
                                        {
                                            "arg_type": 100006, 
                                            "args_list": [
                                                [
                                                    "UNIT_ENTITY", 
                                                    "unit", 
                                                    "local"
                                                ]
                                            ], 
                                            "sub_type": 11
                                        }, 
                                        {
                                            "arg_type": 100004, 
                                            "args_list": [
                                                {
                                                    "arg_type": 100006, 
                                                    "args_list": [
                                                        [
                                                            "UNIT_ENTITY", 
                                                            "unit", 
                                                            "local"
                                                        ]
                                                    ], 
                                                    "sub_type": 11
                                                }
                                            ], 
                                            "sub_type": "UNIT_ENTITY_POINT"
                                        }
                                    ], 
                                    "bp": false, 
                                    "element_id": 1790517250000051, 
                                    "enable": true
                                }
                            ], 
                            "sub_type": 1
                        }
                    ], 
                    "bp": false, 
                    "element_id": 1790517250000075, 
                    "enable": true, 
                    "local_var": {
                        "__tuple__": true, 
                        "items": [
                            {}, 
                            {}
                        ]
                    }
                }
            ], 
            "call_enabled": true, 
            "condition": [
                {
                    "args_list": [
                        {
                            "arg_type": 100006, 
                            "args_list": [
                                [
                                    "UNIT_ENTITY", 
                                    "unit", 
                                    "local"
                                ]
                            ], 
                            "sub_type": 11
                        }
                    ], 
                    "condition_type": "IS_UNIT_ALIVE", 
                    "element_id": 1790517250000067, 
                    "enable": true
                }
            ], 
            "enabled": false, 
            "event": [
                {
                    "args_list": [
                        {
                            "arg_type": 100006, 
                            "args_list": [
                                [
                                    "UNIT_ENTITY", 
                                    "unit", 
                                    "local"
                                ]
                            ], 
                            "sub_type": 11
                        }, 
                        {
                            "arg_type": 100007, 
                            "args_list": [
                                "ET_UNIT_HURT_OTHER"
                            ], 
                            "sub_type": 1
                        }
                    ], 
                    "element_id": 1790517250000001, 
                    "enable": true, 
                    "event_type": "SPECIAL_UNIT_EVENT"
                }
            ], 
            "group_id": 134257764, 
            "is_conf": true, 
            "p_trigger_id": 2132258821, 
            "trigger_id": 1790517250, 
            "trigger_name": "\u5b50\u89e6\u53d1\u5668", 
            "valid": false, 
            "var_data": [
                {
                    "NEW_TIMER": {}, 
                    "UNIT_ENTITY": {}
                }, 
                {}, 
                []
            ]
        }, 
        "2132258821": {
            "action": [
                {
                    "action_type": "SET_VARIABLE", 
                    "args_list": [
                        {
                            "arg_type": 100030, 
                            "args_list": [
                                [
                                    "UNIT_ENTITY", 
                                    "unit", 
                                    "local"
                                ]
                            ], 
                            "sub_type": 1
                        }, 
                        {
                            "arg_type": 100006, 
                            "args_list": [], 
                            "sub_type": "ABILITY_OWNER"
                        }
                    ], 
                    "bp": false, 
                    "element_id": 1790517250000069, 
                    "enable": true
                }, 
                1790517250
            ], 
            "call_enabled": true, 
            "condition": [], 
            "enabled": true, 
            "event": [
                {
                    "args_list": [], 
                    "element_id": 2132258821000001, 
                    "enable": true, 
                    "event_type": "ABILITY_OBTAIN"
                }
            ], 
            "group_id": 134257764, 
            "p_trigger_id": null, 
            "trigger_id": 2132258821, 
            "trigger_name": "\u65b0\u5efa\u89e6\u53d1\u5668", 
            "valid": false, 
            "var_data": [
                {
                    "SFX_ENTITY": {
                        "effect": 0
                    }, 
                    "UNIT_ENTITY": {
                        "unit": 0
                    }
                }, 
                {
                    "effect": 0, 
                    "unit": 0
                }, 
                [
                    "effect", 
                    "unit"
                ]
            ]
        }
    }, 
    "trigger_group_info": [
        {
            "__tuple__": true, 
            "items": [
                1790517250, 
                "\u5b50\u89e6\u53d1\u5668"
            ]
        }, 
        {
            "_trigger_group_": true, 
            "group": [
                {
                    "__tuple__": true, 
                    "items": [
                        2132258821, 
                        "\u65b0\u5efa\u89e6\u53d1\u5668"
                    ]
                }
            ], 
            "key": 134257764, 
            "name": "134257764"
        }
    ], 
    "trigger_version": "1.2", 
    "variable_dict": {
        "UNIT_GROUP": {
            "g": []
        }
    }, 
    "variable_group_info": [
        {
            "__tuple__": true, 
            "items": [
                "g", 
                "g"
            ]
        }
    ], 
    "variable_length_dict": {
        "g": 0
    }
}